test_portal_gun/__init__.py
test_portal_gun/main.py
test_portal_gun-0.3.7.dist-info/entry_points.txt
test_portal_gun-0.3.7.dist-info/WHEEL
test_portal_gun-0.3.7.dist-info/METADATA
test_portal_gun-0.3.7.dist-info/RECORD
