Metadata-Version: 2.1
Name: test-portal-gun
Version: 0.3.7
Summary: 
Author: Alireza
Author-email: alirezaaraby5@gmail.com
Requires-Python: >=3.9,<4.0
Classifier: Programming Language :: Python :: 3
Classifier: Programming Language :: Python :: 3.10
Classifier: Programming Language :: Python :: 3.9
Requires-Dist: typer[all] (>=0.6.1,<0.7.0)
